npcirclepack/__init__.py
npcirclepack/enclose.py
npcirclepack/node.py
npcirclepack/pack.py
npcirclepack/pack_hierarchy.py
npcirclepack-0.1.0.dist-info/LICENSE
npcirclepack-0.1.0.dist-info/METADATA
npcirclepack-0.1.0.dist-info/WHEEL
npcirclepack-0.1.0.dist-info/top_level.txt
npcirclepack-0.1.0.dist-info/RECORD
