Metadata-Version: 2.1
Name: npcirclepack
Version: 0.1.0
Summary: Circle packing utility using numpy arrays.
Home-page: https://github.com/bill-bateman/npcirclepack
Author: Bill Bateman
Author-email: bill@batemanzhou.com
License: ISC License
Platform: UNKNOWN
License-File: LICENSE
Requires-Dist: numpy
